README.md
setup.py
codegen/__init__.py
codegen/app.py
codegen/download.py
codegen/githelper.py
codegen/template_data.py
md_codegen.egg-info/PKG-INFO
md_codegen.egg-info/SOURCES.txt
md_codegen.egg-info/dependency_links.txt
md_codegen.egg-info/requires.txt
md_codegen.egg-info/top_level.txt
scripts/codegen