Metadata-Version: 1.1
Name: md-codegen
Version: 0.4.2
Summary: codegen is a library for generating the infrastructure code of microservices.
Home-page: https://github.com/cao5zy/codegen
Author: Zongying Cao
Author-email: zongying.cao@dxc.com
License: Apache
Platform: UNKNOWN
Classifier: Development Status :: 4 - Beta
Classifier: Intended Audience :: Developers
Classifier: License :: OSI Approved :: Apache Software License
Classifier: Natural Language :: English
Classifier: Operating System :: OS Independent
Classifier: Programming Language :: Python :: 3
Classifier: Topic :: Software Development :: Libraries
